[
  {
    "type": "xy",
    "connectors": [
      0,
      3,
      0,
      3
    ],
    "rotate": 0
  },
  {
    "type": "xy",
    "connectors": [
      0,
      3,
      3,
      3
    ],
    "rotate": 0
  },
  {
    "type": "xyr",
    "connectors": [
      4,
      2,
      0,
      0
    ],
    "rotate": 0
  },
  {},
  {
    "type": "y",
    "connectors": [
      0,
      0,
      0,
      3
    ],
    "rotate": 0
  },
  {},
  {
    "type": "xr",
    "connectors": [
      4,
      3,
      0,
      4
    ],
    "rotate": 180
  },
  {},
  {},
  {
    "type": "xy",
    "connectors": [
      0,
      0,
      4,
      0
    ],
    "rotate": 0
  },
  {
    "type": "xr",
    "connectors": [
      3,
      0,
      4,
      0
    ],
    "rotate": 180
  },
  {},
  {
    "type": "x",
    "connectors": [
      1,
      0,
      4,
      0
    ],
    "rotate": 0
  },
  {},
  {},
  {
    "type": "r",
    "connectors": [
      4,
      1,
      0,
      0
    ],
    "rotate": 270
  },
  {
    "type": "y",
    "connectors": [
      0,
      4,
      4,
      1
    ],
    "rotate": 0
  },
  {},
  {},
  {
    "type": "xr",
    "connectors": [
      4,
      0,
      4,
      4
    ],
    "rotate": 90
  },
  {
    "type": "xyr",
    "connectors": [
      0,
      4,
      1,
      0
    ],
    "rotate": 270
  },
  {},
  {
    "type": "r",
    "connectors": [
      4,
      0,
      0,
      2
    ],
    "rotate": 270
  },
  {},
  {}
]